genshin_data/__init__.py
genshin_data/genshin_data.py
genshin_data/min/data_chinese-simplified.min.json
genshin_data/min/data_chinese-traditional.min.json
genshin_data/min/data_english.min.json
genshin_data/min/data_french.min.json
genshin_data/min/data_german.min.json
genshin_data/min/data_indonesian.min.json
genshin_data/min/data_italian.min.json
genshin_data/min/data_japanese.min.json
genshin_data/min/data_korean.min.json
genshin_data/min/data_portuguese.min.json
genshin_data/min/data_russian.min.json
genshin_data/min/data_spanish.min.json
genshin_data/min/data_thai.min.json
genshin_data/min/data_turkish.min.json
genshin_data/min/data_vietnamese.min.json
genshin_data/types/__init__.py
genshin_data/types/achievement.py
genshin_data/types/artifact.py
genshin_data/types/character.py
genshin_data/types/common_material.py
genshin_data/types/domain.py
genshin_data/types/elemental_stone_materials.py
genshin_data/types/exp.py
genshin_data/types/fishing.py
genshin_data/types/food.py
genshin_data/types/furnishing.py
genshin_data/types/genshin_data.py
genshin_data/types/ingredient.py
genshin_data/types/jewel_material.py
genshin_data/types/local_material.py
genshin_data/types/potion.py
genshin_data/types/talent_lvl_up_material.py
genshin_data/types/tcg_action.py
genshin_data/types/tcg_character.py
genshin_data/types/tcg_monster.py
genshin_data/types/weapon.py
genshin_data/types/weapon_primary_material.py
genshin_data/types/weapon_secondary_material.py
genshin_data-0.1.0.dist-info/LICENSE
genshin_data-0.1.0.dist-info/METADATA
genshin_data-0.1.0.dist-info/WHEEL
genshin_data-0.1.0.dist-info/top_level.txt
genshin_data-0.1.0.dist-info/RECORD
