Metadata-Version: 2.1
Name: genshin-data
Version: 0.1.0
Summary: Python version of https://github.com/dvaJi/genshin-data
Author: dvaJi, Victorsitou
License: MIT
Project-URL: Homepage, https://github.com/Victorsitou/genshin-data
Project-URL: Bug Tracker, https://github.com/Victorsitou/genshin-data/issues
Requires-Python: >=3.8
License-File: LICENSE
Requires-Dist: pydantic (<1.11.0,>=1.10.0)
